{
  "SB10": {
    "top3": {
      "ledgerPath": "C:\\Users\\voide\\Downloads\\POLYPROPHET-main\\POLYPROPHET-main\\debug\\final_set_scan\\top3_robust\\hybrid_replay_executed_ledger.json",
      "label": "final_set_scan/top3_robust",
      "trades": 160,
      "wins": 149,
      "winRate": 0.93125,
      "winRateLCB": 0.8810959503315198,
      "days": 109.98958333333333,
      "tradesPerDay": 1.4546832086371817,
      "best": {
        "stakeFraction": 0.3,
        "meanEnd": 1995.700910021914,
        "medianEnd": 504.301180428203,
        "minEnd": 34.87348755107901,
        "pEndBelowStart": 0,
        "pEndBelow5": 0,
        "worstEnd": 34.87348755107901,
        "worstBlocked": 7,
        "worstExecuted": 153,
        "worstHaltMinOrder": 0
      },
      "stakeRows": [
        {
          "stakeFraction": 0.05,
          "meanEnd": 28.881880337228157,
          "medianEnd": 26.63338116635122,
          "minEnd": 16.76083567002321,
          "pEndBelowStart": 0,
          "pEndBelow5": 0,
          "worstEnd": 16.76083567002321,
          "worstBlocked": 0,
          "worstExecuted": 160,
          "worstHaltMinOrder": 0
        },
        {
          "stakeFraction": 0.075,
          "meanEnd": 41.959075995576875,
          "medianEnd": 35.59046361931627,
          "minEnd": 17.75206203843141,
          "pEndBelowStart": 0,
          "pEndBelow5": 0,
          "worstEnd": 17.75206203843141,
          "worstBlocked": 0,
          "worstExecuted": 160,
          "worstHaltMinOrder": 0
        },
        {
          "stakeFraction": 0.1,
          "meanEnd": 68.24554710106345,
          "medianEnd": 52.61435579952989,
          "minEnd": 20.04629885166758,
          "pEndBelowStart": 0,
          "pEndBelow5": 0,
          "worstEnd": 20.04629885166758,
          "worstBlocked": 0,
          "worstExecuted": 160,
          "worstHaltMinOrder": 0
        },
        {
          "stakeFraction": 0.15,
          "meanEnd": 185.82151779215016,
          "medianEnd": 112.49393707427488,
          "minEnd": 26.685596204954344,
          "pEndBelowStart": 0,
          "pEndBelow5": 0,
          "worstEnd": 26.685596204954344,
          "worstBlocked": 0,
          "worstExecuted": 160,
          "worstHaltMinOrder": 0
        },
        {
          "stakeFraction": 0.2,
          "meanEnd": 371.85974689025454,
          "medianEnd": 177.0087168486294,
          "minEnd": 28.586650373656624,
          "pEndBelowStart": 0,
          "pEndBelow5": 0,
          "worstEnd": 28.586650373656624,
          "worstBlocked": 6,
          "worstExecuted": 154,
          "worstHaltMinOrder": 0
        },
        {
          "stakeFraction": 0.25,
          "meanEnd": 914.7362957847621,
          "medianEnd": 319.10614091431614,
          "minEnd": 31.914661495713222,
          "pEndBelowStart": 0,
          "pEndBelow5": 0,
          "worstEnd": 31.914661495713222,
          "worstBlocked": 7,
          "worstExecuted": 153,
          "worstHaltMinOrder": 0
        },
        {
          "stakeFraction": 0.3,
          "meanEnd": 1995.700910021914,
          "medianEnd": 504.301180428203,
          "minEnd": 34.87348755107901,
          "pEndBelowStart": 0,
          "pEndBelow5": 0,
          "worstEnd": 34.87348755107901,
          "worstBlocked": 7,
          "worstExecuted": 153,
          "worstHaltMinOrder": 0
        }
      ]
    },
    "top5": {
      "ledgerPath": "C:\\Users\\voide\\Downloads\\POLYPROPHET-main\\POLYPROPHET-main\\debug\\final_set_scan\\top5_robust\\hybrid_replay_executed_ledger.json",
      "label": "final_set_scan/top5_robust",
      "trades": 242,
      "wins": 217,
      "winRate": 0.8966942148760331,
      "winRateLCB": 0.851947320958714,
      "days": 109.98958333333333,
      "tradesPerDay": 2.2002083530637373,
      "best": {
        "stakeFraction": 0.075,
        "meanEnd": 40.92807416733151,
        "medianEnd": 31.25737588188482,
        "minEnd": 11.860113516460958,
        "pEndBelowStart": 0,
        "pEndBelow5": 0,
        "worstEnd": 11.860113516460958,
        "worstBlocked": 5,
        "worstExecuted": 237,
        "worstHaltMinOrder": 0
      },
      "stakeRows": [
        {
          "stakeFraction": 0.05,
          "meanEnd": 28.26615392939572,
          "medianEnd": 24.616980499823676,
          "minEnd": 11.858973965025204,
          "pEndBelowStart": 0,
          "pEndBelow5": 0,
          "worstEnd": 11.858973965025204,
          "worstBlocked": 5,
          "worstExecuted": 237,
          "worstHaltMinOrder": 0
        },
        {
          "stakeFraction": 0.075,
          "meanEnd": 40.92807416733151,
          "medianEnd": 31.25737588188482,
          "minEnd": 11.860113516460958,
          "pEndBelowStart": 0,
          "pEndBelow5": 0,
          "worstEnd": 11.860113516460958,
          "worstBlocked": 5,
          "worstExecuted": 237,
          "worstHaltMinOrder": 0
        },
        {
          "stakeFraction": 0.1,
          "meanEnd": 65.82376706017759,
          "medianEnd": 40.80121973090622,
          "minEnd": 11.528921359451354,
          "pEndBelowStart": 0,
          "pEndBelow5": 0,
          "worstEnd": 11.528921359451354,
          "worstBlocked": 6,
          "worstExecuted": 236,
          "worstHaltMinOrder": 0
        },
        {
          "stakeFraction": 0.15,
          "meanEnd": 149.86552068724114,
          "medianEnd": 61.12906148838941,
          "minEnd": 1.021957822178308,
          "pEndBelowStart": 0.03333333333333333,
          "pEndBelow5": 0.03333333333333333,
          "worstEnd": 1.021957822178308,
          "worstBlocked": 127,
          "worstExecuted": 115,
          "worstHaltMinOrder": 117
        },
        {
          "stakeFraction": 0.2,
          "meanEnd": 394.84289395032727,
          "medianEnd": 105.11771643337974,
          "minEnd": 0.8907926826276694,
          "pEndBelowStart": 0.13333333333333333,
          "pEndBelow5": 0.13333333333333333,
          "worstEnd": 0.9347610137665133,
          "worstBlocked": 133,
          "worstExecuted": 109,
          "worstHaltMinOrder": 117
        },
        {
          "stakeFraction": 0.25,
          "meanEnd": 1155.1101847833552,
          "medianEnd": 177.57396646710012,
          "minEnd": 1.142894981947383,
          "pEndBelowStart": 0.2,
          "pEndBelow5": 0.2,
          "worstEnd": 1.668579583233167,
          "worstBlocked": 144,
          "worstExecuted": 98,
          "worstHaltMinOrder": 127
        },
        {
          "stakeFraction": 0.3,
          "meanEnd": 2642.411220505259,
          "medianEnd": 294.2863970543631,
          "minEnd": 0.891648951516757,
          "pEndBelowStart": 0.36666666666666664,
          "pEndBelow5": 0.36666666666666664,
          "worstEnd": 1.6799468660956411,
          "worstBlocked": 182,
          "worstExecuted": 60,
          "worstHaltMinOrder": 173
        }
      ]
    },
    "opt8": {
      "ledgerPath": "C:\\Users\\voide\\Downloads\\POLYPROPHET-main\\POLYPROPHET-main\\debug\\final_full_default\\hybrid_replay_executed_ledger.json",
      "label": "final_full_default",
      "trades": 522,
      "wins": 453,
      "winRate": 0.867816091954023,
      "winRateLCB": 0.8360556418370404,
      "days": 110.46875,
      "tradesPerDay": 4.725318246110326,
      "best": {
        "stakeFraction": 0.1,
        "meanEnd": 393.17678954104514,
        "medianEnd": 101.36597322345227,
        "minEnd": 1.048382594824787,
        "pEndBelowStart": 0.3,
        "pEndBelow5": 0.3,
        "worstEnd": 1.5340772395506719,
        "worstBlocked": 447,
        "worstExecuted": 75,
        "worstHaltMinOrder": 437
      },
      "stakeRows": [
        {
          "stakeFraction": 0.05,
          "meanEnd": 63.010643854951695,
          "medianEnd": 40.00008193378983,
          "minEnd": 0.8489900691670998,
          "pEndBelowStart": 0.3,
          "pEndBelow5": 0.3,
          "worstEnd": 1.522636728392348,
          "worstBlocked": 442,
          "worstExecuted": 80,
          "worstHaltMinOrder": 431
        },
        {
          "stakeFraction": 0.075,
          "meanEnd": 166.56793761663656,
          "medianEnd": 64.68217327610053,
          "minEnd": 0.8489900691670998,
          "pEndBelowStart": 0.3,
          "pEndBelow5": 0.3,
          "worstEnd": 1.522636728392348,
          "worstBlocked": 442,
          "worstExecuted": 80,
          "worstHaltMinOrder": 431
        },
        {
          "stakeFraction": 0.1,
          "meanEnd": 393.17678954104514,
          "medianEnd": 101.36597322345227,
          "minEnd": 1.048382594824787,
          "pEndBelowStart": 0.3,
          "pEndBelow5": 0.3,
          "worstEnd": 1.5340772395506719,
          "worstBlocked": 447,
          "worstExecuted": 75,
          "worstHaltMinOrder": 437
        },
        {
          "stakeFraction": 0.15,
          "meanEnd": 3269.107623455861,
          "medianEnd": 247.13137864298443,
          "minEnd": 0.8543904913457718,
          "pEndBelowStart": 0.4666666666666667,
          "pEndBelow5": 0.4666666666666667,
          "worstEnd": 1.1100281483640684,
          "worstBlocked": 457,
          "worstExecuted": 65,
          "worstHaltMinOrder": 442
        },
        {
          "stakeFraction": 0.2,
          "meanEnd": 15279.927450275476,
          "medianEnd": 1.4947384337490595,
          "minEnd": 0.8563572426375196,
          "pEndBelowStart": 0.5333333333333333,
          "pEndBelow5": 0.5333333333333333,
          "worstEnd": 1.002068831496996,
          "worstBlocked": 465,
          "worstExecuted": 57,
          "worstHaltMinOrder": 442
        },
        {
          "stakeFraction": 0.25,
          "meanEnd": 89902.98437544629,
          "medianEnd": 1.3302995361749845,
          "minEnd": 0.8694294162179745,
          "pEndBelowStart": 0.7666666666666667,
          "pEndBelow5": 0.7666666666666667,
          "worstEnd": 1.2215878137485972,
          "worstBlocked": 472,
          "worstExecuted": 50,
          "worstHaltMinOrder": 453
        },
        {
          "stakeFraction": 0.3,
          "meanEnd": 83985.36071910008,
          "medianEnd": 1.3022147107863207,
          "minEnd": 0.8412982892799526,
          "pEndBelowStart": 0.9,
          "pEndBelow5": 0.9,
          "worstEnd": 1.337428636052807,
          "worstBlocked": 480,
          "worstExecuted": 42,
          "worstHaltMinOrder": 469
        }
      ]
    }
  },
  "SB5": {
    "top3": {
      "ledgerPath": "C:\\Users\\voide\\Downloads\\POLYPROPHET-main\\POLYPROPHET-main\\debug\\final_set_scan\\top3_robust\\hybrid_replay_executed_ledger.json",
      "label": "final_set_scan/top3_robust",
      "trades": 160,
      "wins": 149,
      "winRate": 0.93125,
      "winRateLCB": 0.8810959503315198,
      "days": 109.98958333333333,
      "tradesPerDay": 1.4546832086371817,
      "best": {
        "stakeFraction": 0.3,
        "meanEnd": 998.0239878144829,
        "medianEnd": 252.1505902141015,
        "minEnd": 19.15987554127422,
        "pEndBelowStart": 0,
        "pEndBelow5": 0,
        "worstEnd": 19.15987554127422,
        "worstBlocked": 7,
        "worstExecuted": 153,
        "worstHaltMinOrder": 0
      },
      "stakeRows": [
        {
          "stakeFraction": 0.05,
          "meanEnd": 21.302310309822744,
          "medianEnd": 19.821356837084696,
          "minEnd": 11.760835670023184,
          "pEndBelowStart": 0,
          "pEndBelow5": 0,
          "worstEnd": 11.760835670023184,
          "worstBlocked": 0,
          "worstExecuted": 160,
          "worstHaltMinOrder": 0
        },
        {
          "stakeFraction": 0.075,
          "meanEnd": 27.287804094173268,
          "medianEnd": 23.47295784209752,
          "minEnd": 11.760922018811348,
          "pEndBelowStart": 0,
          "pEndBelow5": 0,
          "worstEnd": 11.760922018811348,
          "worstBlocked": 0,
          "worstExecuted": 160,
          "worstHaltMinOrder": 0
        },
        {
          "stakeFraction": 0.1,
          "meanEnd": 38.76790128647156,
          "medianEnd": 30.679002883693087,
          "minEnd": 12.112798662277376,
          "pEndBelowStart": 0,
          "pEndBelow5": 0,
          "worstEnd": 12.112798662277376,
          "worstBlocked": 0,
          "worstExecuted": 160,
          "worstHaltMinOrder": 0
        },
        {
          "stakeFraction": 0.15,
          "meanEnd": 93.58694388347735,
          "medianEnd": 56.57553112894736,
          "minEnd": 14.569435931569043,
          "pEndBelowStart": 0,
          "pEndBelow5": 0,
          "worstEnd": 14.569435931569043,
          "worstBlocked": 0,
          "worstExecuted": 160,
          "worstHaltMinOrder": 0
        },
        {
          "stakeFraction": 0.2,
          "meanEnd": 186.08319703504466,
          "medianEnd": 88.5043584243147,
          "minEnd": 15.187850634303496,
          "pEndBelowStart": 0,
          "pEndBelow5": 0,
          "worstEnd": 15.187850634303496,
          "worstBlocked": 6,
          "worstExecuted": 154,
          "worstHaltMinOrder": 0
        },
        {
          "stakeFraction": 0.25,
          "meanEnd": 457.49067937130275,
          "medianEnd": 159.55307045715807,
          "minEnd": 17.10645433854667,
          "pEndBelowStart": 0,
          "pEndBelow5": 0,
          "worstEnd": 17.10645433854667,
          "worstBlocked": 7,
          "worstExecuted": 153,
          "worstHaltMinOrder": 0
        },
        {
          "stakeFraction": 0.3,
          "meanEnd": 998.0239878144829,
          "medianEnd": 252.1505902141015,
          "minEnd": 19.15987554127422,
          "pEndBelowStart": 0,
          "pEndBelow5": 0,
          "worstEnd": 19.15987554127422,
          "worstBlocked": 7,
          "worstExecuted": 153,
          "worstHaltMinOrder": 0
        }
      ]
    },
    "top5": {
      "ledgerPath": "C:\\Users\\voide\\Downloads\\POLYPROPHET-main\\POLYPROPHET-main\\debug\\final_set_scan\\top5_robust\\hybrid_replay_executed_ledger.json",
      "label": "final_set_scan/top5_robust",
      "trades": 242,
      "wins": 217,
      "winRate": 0.8966942148760331,
      "winRateLCB": 0.851947320958714,
      "days": 109.98958333333333,
      "tradesPerDay": 2.2002083530637373,
      "best": {
        "stakeFraction": 0.1,
        "meanEnd": 38.06853842687659,
        "medianEnd": 24.151877901413805,
        "minEnd": 1.2244957571276216,
        "pEndBelowStart": 0.13333333333333333,
        "pEndBelow5": 0.13333333333333333,
        "worstEnd": 1.5795777767650478,
        "worstBlocked": 175,
        "worstExecuted": 67,
        "worstHaltMinOrder": 173
      },
      "stakeRows": [
        {
          "stakeFraction": 0.05,
          "meanEnd": 19.745187818446244,
          "medianEnd": 17.629627874281805,
          "minEnd": 1.2244957571276216,
          "pEndBelowStart": 0.13333333333333333,
          "pEndBelow5": 0.13333333333333333,
          "worstEnd": 1.5795777767650478,
          "worstBlocked": 175,
          "worstExecuted": 67,
          "worstHaltMinOrder": 173
        },
        {
          "stakeFraction": 0.075,
          "meanEnd": 26.27630181041378,
          "medianEnd": 19.757781675827133,
          "minEnd": 1.2244957571276216,
          "pEndBelowStart": 0.13333333333333333,
          "pEndBelow5": 0.13333333333333333,
          "worstEnd": 1.5795777767650478,
          "worstBlocked": 175,
          "worstExecuted": 67,
          "worstHaltMinOrder": 173
        },
        {
          "stakeFraction": 0.1,
          "meanEnd": 38.06853842687659,
          "medianEnd": 24.151877901413805,
          "minEnd": 1.2244957571276216,
          "pEndBelowStart": 0.13333333333333333,
          "pEndBelow5": 0.13333333333333333,
          "worstEnd": 1.5795777767650478,
          "worstBlocked": 175,
          "worstExecuted": 67,
          "worstHaltMinOrder": 173
        },
        {
          "stakeFraction": 0.15,
          "meanEnd": 76.65655813433291,
          "medianEnd": 40.03163512750423,
          "minEnd": 1.1309422554394213,
          "pEndBelowStart": 0.26666666666666666,
          "pEndBelow5": 0.26666666666666666,
          "worstEnd": 1.5795777767650478,
          "worstBlocked": 175,
          "worstExecuted": 67,
          "worstHaltMinOrder": 173
        },
        {
          "stakeFraction": 0.2,
          "meanEnd": 199.71043015544345,
          "medianEnd": 64.0907432400538,
          "minEnd": 1.0026117542117525,
          "pEndBelowStart": 0.3,
          "pEndBelow5": 0.3,
          "worstEnd": 1.631193773048222,
          "worstBlocked": 179,
          "worstExecuted": 63,
          "worstHaltMinOrder": 173
        },
        {
          "stakeFraction": 0.25,
          "meanEnd": 572.3803466414397,
          "medianEnd": 96.13527211419091,
          "minEnd": 0.8582884538487064,
          "pEndBelowStart": 0.4,
          "pEndBelow5": 0.4,
          "worstEnd": 0.8582884538487064,
          "worstBlocked": 182,
          "worstExecuted": 60,
          "worstHaltMinOrder": 173
        },
        {
          "stakeFraction": 0.3,
          "meanEnd": 1291.5332766368213,
          "medianEnd": 1.5834638495407152,
          "minEnd": 0.9156350153057122,
          "pEndBelowStart": 0.5666666666666667,
          "pEndBelow5": 0.5666666666666667,
          "worstEnd": 1.101668391214536,
          "worstBlocked": 185,
          "worstExecuted": 57,
          "worstHaltMinOrder": 174
        }
      ]
    },
    "opt8": {
      "ledgerPath": "C:\\Users\\voide\\Downloads\\POLYPROPHET-main\\POLYPROPHET-main\\debug\\final_full_default\\hybrid_replay_executed_ledger.json",
      "label": "final_full_default",
      "trades": 522,
      "wins": 453,
      "winRate": 0.867816091954023,
      "winRateLCB": 0.8360556418370404,
      "days": 110.46875,
      "tradesPerDay": 4.725318246110326,
      "best": {
        "stakeFraction": 0.1,
        "meanEnd": 230.47863269121726,
        "medianEnd": 1.2789217225013974,
        "minEnd": 0.8543822834374944,
        "pEndBelowStart": 0.6333333333333333,
        "pEndBelow5": 0.6333333333333333,
        "worstEnd": 1.2789217225013974,
        "worstBlocked": 424,
        "worstExecuted": 98,
        "worstHaltMinOrder": 416
      },
      "stakeRows": [
        {
          "stakeFraction": 0.05,
          "meanEnd": 35.87534670756777,
          "medianEnd": 1.2789217225013974,
          "minEnd": 0.8543822834374944,
          "pEndBelowStart": 0.6333333333333333,
          "pEndBelow5": 0.6333333333333333,
          "worstEnd": 1.2789217225013974,
          "worstBlocked": 424,
          "worstExecuted": 98,
          "worstHaltMinOrder": 416
        },
        {
          "stakeFraction": 0.075,
          "meanEnd": 92.38020394302711,
          "medianEnd": 1.2789217225013974,
          "minEnd": 0.8543822834374944,
          "pEndBelowStart": 0.6333333333333333,
          "pEndBelow5": 0.6333333333333333,
          "worstEnd": 1.2789217225013974,
          "worstBlocked": 424,
          "worstExecuted": 98,
          "worstHaltMinOrder": 416
        },
        {
          "stakeFraction": 0.1,
          "meanEnd": 230.47863269121726,
          "medianEnd": 1.2789217225013974,
          "minEnd": 0.8543822834374944,
          "pEndBelowStart": 0.6333333333333333,
          "pEndBelow5": 0.6333333333333333,
          "worstEnd": 1.2789217225013974,
          "worstBlocked": 424,
          "worstExecuted": 98,
          "worstHaltMinOrder": 416
        },
        {
          "stakeFraction": 0.15,
          "meanEnd": 1740.0114078795689,
          "medianEnd": 1.257976572252216,
          "minEnd": 0.8398495617576421,
          "pEndBelowStart": 0.7333333333333333,
          "pEndBelow5": 0.7333333333333333,
          "worstEnd": 1.2789217225013974,
          "worstBlocked": 424,
          "worstExecuted": 98,
          "worstHaltMinOrder": 416
        },
        {
          "stakeFraction": 0.2,
          "meanEnd": 821.9446463149545,
          "medianEnd": 1.2602768869371417,
          "minEnd": 0.8398523053602602,
          "pEndBelowStart": 0.9333333333333333,
          "pEndBelow5": 0.9333333333333333,
          "worstEnd": 1.335026231961562,
          "worstBlocked": 490,
          "worstExecuted": 32,
          "worstHaltMinOrder": 481
        },
        {
          "stakeFraction": 0.25,
          "meanEnd": 12054.880625792457,
          "medianEnd": 1.2532560363378478,
          "minEnd": 0.8596123787141039,
          "pEndBelowStart": 0.8666666666666667,
          "pEndBelow5": 0.8666666666666667,
          "worstEnd": 0.9493667052001645,
          "worstBlocked": 490,
          "worstExecuted": 32,
          "worstHaltMinOrder": 481
        },
        {
          "stakeFraction": 0.3,
          "meanEnd": 5982.1533122797255,
          "medianEnd": 1.2544276360834656,
          "minEnd": 0.8394764953677973,
          "pEndBelowStart": 0.9333333333333333,
          "pEndBelow5": 0.9333333333333333,
          "worstEnd": 1.4412927360138137,
          "worstBlocked": 491,
          "worstExecuted": 31,
          "worstHaltMinOrder": 485
        }
      ]
    }
  }
}